mini_scripts/__init__.py
mini_scripts/datetime.py
mini_scripts/files.py
mini_scripts/parsers.py
mini_scripts/text.py
mini_scripts/versions.py
mini_scripts/vk.py
mini_scripts-0.1.0.dist-info/WHEEL
mini_scripts-0.1.0.dist-info/METADATA
mini_scripts-0.1.0.dist-info/RECORD
